src/copal_mav/__init__.py
src/copal_mav/copal.py
copal-0.0.1.dist-info/METADATA
copal-0.0.1.dist-info/WHEEL
copal-0.0.1.dist-info/licenses/LICENSE
copal-0.0.1.dist-info/RECORD
