Metadata-Version: 2.1
Name: copal
Version: 0.0.1
Summary: A Color Palette Library
Project-URL: Homepage, https://github.com/pypa/sampleproject
Project-URL: Bug Tracker, https://github.com/pypa/sampleproject/issues
Author-email: "MARTIN A. VILLANUEVA" <m21a@mit.edu>
License-File: LICENSE
Classifier: License :: OSI Approved :: MIT License
Classifier: Operating System :: OS Independent
Classifier: Programming Language :: Python :: 3
Requires-Python: >=3.7
